aigraphcodescan-4.0.14.dist-info/licenses/LICENSE
src/aigraphcodescan/__main__.py
src/aigraphcodescan/app.py
src/aigraphcodescan.egg-info/PKG-INFO
src/aigraphcodescan.egg-info/SOURCES.txt
src/aigraphcodescan.egg-info/dependency_links.txt
src/aigraphcodescan.egg-info/entry_points.txt
src/aigraphcodescan.egg-info/top_level.txt
aigraphcodescan-4.0.14.dist-info/METADATA
aigraphcodescan-4.0.14.dist-info/WHEEL
aigraphcodescan-4.0.14.dist-info/entry_points.txt
aigraphcodescan-4.0.14.dist-info/top_level.txt
aigraphcodescan-4.0.14.dist-info/RECORD
