Metadata-Version: 2.4
Name: aigraphcodescan
Version: 4.0.14
Summary: A tool for security review of code using graph-based analysis
Author-email: Marcin Kozlowski <marcinguy@gmail.com>
License-Expression: AGPL-3.0-only
Classifier: Programming Language :: Python :: 3
Classifier: Operating System :: OS Independent
Requires-Python: >=3.6
License-File: LICENSE
Requires-Dist: neo4j>=4.0.0
Requires-Dist: fast_graphrag>=0.0.4
Requires-Dist: logging
Requires-Dist: argparse
Dynamic: license-file
